{
    "page": 1,
    "pageSize": 5,
    "totalPosts": 30,
    "totalPages": 6,
    "posts": [
        {
            "title": "10 AI Trends to Watch in 2023",
            "author": "Jane Doe",
            "date": "2023-01-02",
            "category": "AI",
            "tags": [
                "AI",
                "Machine Learning",
                "Deep Learning",
                "Neural Networks",
                "Natural Language Processing"
            ],
            "content": "As we enter a new year, it's important to take stock of where AI is heading. Here are 10 trends to watch in 2023, including the rise of responsible AI, the use of AI in personalized medicine, and the impact of quantum computing on AI algorithms.",
            "id": "BLOG100",
            "img": "https://source.unsplash.com/random/100x100?person,portrait"
        },
        {
            "title": "Why Software Engineering Is More Than Just Coding",
            "author": "John Smith",
            "date": "2023-02-14",
            "category": "Software Engineering",
            "tags": [
                "Software Development",
                "Agile",
                "Project Management",
                "Coding",
                "Testing"
            ],
            "content": "Software engineering is often thought of as just writing code, but it's much more than that. This post explores the key skills needed to be a successful software engineer, including communication, collaboration, project management, and testing.",
            "id": "BLOG200",
            "img": "https://source.unsplash.com/random/100x100?person,portrait"
        },
        {
            "title": "How to Build a Successful Career in Web Development",
            "author": "Samantha Lee",
            "date": "2023-03-01",
            "category": "Web Development",
            "tags": [
                "Web Development",
                "Career",
                "Skills",
                "Portfolio",
                "Networking"
            ],
            "content": "Web development is a rapidly growing field with many career opportunities. This post outlines the key skills needed to succeed in web development, as well as tips for building a strong portfolio, networking, and finding the right job.",
            "id": "BLOG300",
            "img": "https://source.unsplash.com/random/100x100?person,portrait"
        },
        {
            "title": "The Ethics of AI: Challenges and Opportunities",
            "author": "David Chen",
            "date": "2023-02-05",
            "category": "AI",
            "tags": [
                "AI",
                "Ethics",
                "Responsible AI",
                "Bias",
                "Privacy"
            ],
            "content": "As AI becomes more pervasive in our lives, it's important to consider the ethical implications of its use. This post explores the challenges and opportunities of responsible AI, including bias, privacy, and accountability.",
            "id": "BLOG400",
            "img": "https://source.unsplash.com/random/100x100?person,portrait"
        },
        {
            "title": "5 Key Skills for Success in Software Engineering",
            "author": "Megan Jones",
            "date": "2023-01-20",
            "category": "Software Engineering",
            "tags": [
                "Software Development",
                "Agile",
                "Communication",
                "Testing",
                "Problem-Solving"
            ],
            "content": "Software engineering requires a range of skills beyond coding. This post outlines five key skills for success in software engineering, including communication, problem-solving, testing, and collaboration.",
            "id": "BLOG500",
            "img": "https://source.unsplash.com/random/100x100?person,portrait"
        }
    ]
}